timeoutlib.py
timeoutlib-0.1.0.dist-info/LICENSE
timeoutlib-0.1.0.dist-info/WHEEL
timeoutlib-0.1.0.dist-info/METADATA
timeoutlib-0.1.0.dist-info/RECORD
