Metadata-Version: 2.1
Name: timeoutlib
Version: 0.1.0
Summary: Timeout wrapper utilities
Home-page: https://github.com/a2d24/timeoutlib
License: MIT
Keywords: timeout,signal,SIGALRM
Author: Imtiaz Mangerah
Author-email: Imtiaz_Mangerah@a2d24.com
Requires-Python: >=3.6,<4.0
Classifier: License :: OSI Approved :: MIT License
Classifier: Programming Language :: Python :: 3
Classifier: Programming Language :: Python :: 3.10
Classifier: Programming Language :: Python :: 3.6
Classifier: Programming Language :: Python :: 3.7
Classifier: Programming Language :: Python :: 3.8
Classifier: Programming Language :: Python :: 3.9
Project-URL: Documentation, https://github.com/a2d24/timeoutlib
Project-URL: Repository, https://github.com/a2d24/timeoutlib
